hledger_utils/__init__.py
hledger_utils/utils.py
hledger_utils/version.py
hledger_utils/commands/__init__.py
hledger_utils/commands/edit.py
hledger_utils/commands/plot.py
tests/__init__.py
tests/test_hledger_edit.py
tests/test_hledger_plot.py
tests/test_utils.py
hledger_utils-1.14.0.dist-info/CC-BY-4.0.txt
hledger_utils-1.14.0.dist-info/CC0-1.0.txt
hledger_utils-1.14.0.dist-info/GPL-3.0-or-later.txt
hledger_utils-1.14.0.dist-info/METADATA
hledger_utils-1.14.0.dist-info/WHEEL
hledger_utils-1.14.0.dist-info/entry_points.txt
hledger_utils-1.14.0.dist-info/top_level.txt
hledger_utils-1.14.0.dist-info/RECORD
