Metadata-Version: 2.1
Name: hledger-utils
Version: 1.14.0
Summary: Utilities enhancing hledger
Home-page: https://gitlab.com/nobodyinperson/hledger-utils
Author: Yann Buechau
Author-email: nobodyinperson@posteo.de
License: GPLv3
Keywords: hledger,extension,plugin,plaintextaccounting
Classifier: License :: OSI Approved :: GNU General Public License v3 (GPLv3)
Classifier: License :: CC0 1.0 Universal (CC0 1.0) Public Domain Dedication
Requires-Python: >=3.8
License-File: LICENSES/CC-BY-4.0.txt
License-File: LICENSES/CC0-1.0.txt
License-File: LICENSES/GPL-3.0-or-later.txt
Requires-Dist: rich
Requires-Dist: psutil
Requires-Dist: matplotlib
Requires-Dist: pandas
Requires-Dist: cycler
Requires-Dist: numpy
Requires-Dist: scipy
Requires-Dist: drawilleplot
Requires-Dist: asteval
